setup.py
digNationalityExtractor/__init__.py
digNationalityExtractor/names.py
digNationalityExtractor/names_helper.py
digNationalityExtractor.egg-info/PKG-INFO
digNationalityExtractor.egg-info/SOURCES.txt
digNationalityExtractor.egg-info/dependency_links.txt
digNationalityExtractor.egg-info/requires.txt
digNationalityExtractor.egg-info/top_level.txt
test/__init__.py
test/test_nationality_extractor.py