Metadata-Version: 1.1
Name: digNationalityExtractor
Version: 0.3.0
Summary: digNationalityExtractor
Home-page: https://github.com/usc-isi-i2/dig-nationality-extractor
Author: Lingzhe Teng
Author-email: zwein27@gmail.com
License: UNKNOWN
Download-URL: https://github.com/usc-isi-i2/dig-nationality-extractor
Keywords: nationality,extractor
Platform: UNKNOWN
